MANIFEST.in
README
setup.py
PySCUBA.egg-info/PKG-INFO
PySCUBA.egg-info/SOURCES.txt
PySCUBA.egg-info/dependency_links.txt
PySCUBA.egg-info/entry_points.txt
PySCUBA.egg-info/requires.txt
PySCUBA.egg-info/top_level.txt
src/PySCUBA/Gap_stats.py
src/PySCUBA/Preprocessing.py
src/PySCUBA/PySCUBA_design.py
src/PySCUBA/SCUBA_core.py
src/PySCUBA/Tree_classes.py
src/PySCUBA/__init__.py
src/PySCUBA/__main__.py
src/PySCUBA/__version__.py