Metadata-Version: 1.1
Name: PySCUBA
Version: 0.1.1
Summary: Python for Single-cell Clustering Using Bifurcation Analysis
Home-page: https://github.com/GGiecold/PySCUBA
Author: Gregory Giecold
Author-email: ggiecold@jimmy.harvard.edu
License: MIT License
Download-URL: https://github.com/GGiecold/PySCUBA
Keywords: bioinformatics biology clustering cytometry gap-statistics genomics machine-learning pattern-recognition PCR principal-curve qPCR RNASeq single-cell time-series unsupervised-learning
Platform: Any
Classifier: Development Status :: 4 - Beta
Classifier: Environment :: Console
Classifier: Intended Audience :: End Users/Desktop
Classifier: Intended Audience :: Developers
Classifier: Intended Audience :: Healthcare Industry
Classifier: Intended Audience :: Science/Research
Classifier: License :: OSI Approved :: MIT License
Classifier: Natural Language :: English
Classifier: Operating System :: MacOS :: MacOS X
Classifier: Operating System :: Microsoft
Classifier: Operating System :: POSIX
Classifier: Programming Language :: Python :: 2.7
Classifier: Topic :: Scientific/Engineering
Classifier: Topic :: Scientific/Engineering :: Bio-Informatics
Classifier: Topic :: Scientific/Engineering :: Visualization
Classifier: Topic :: Scientific/Engineering :: Mathematics
Classifier: Topic :: Software Development :: User Interfaces
